Metadata-Version: 1.2
Name: image-augmentor
Version: 0.1.5
Summary: An image augmentation library for machine learning
Home-page: https://github.com/michaelmendoza/image_augmentor
Author: Michael Mendoza
Author-email: iammichaelmendoza@gmail.com
License: GPL
Platform: UNKNOWN
Requires-Python: >=2.7
